{
	"class" : {
		"example" : "brunobb 07/24/2023 06:47",
		"newFromFile:root:" : "brunobb 07/24/2023 06:41",
		"newFromStream:root:" : "brunobb 07/24/2023 06:42",
		"parseLine:" : "brunobb 07/24/2023 06:48" },
	"instance" : {
		"assert:onErrorDisplay:" : "brunobb 07/24/2023 06:35",
		"attributeAtIndex:ifNone:" : "brunobb 07/24/2023 06:35",
		"attributes" : "brunobb 07/24/2023 06:35",
		"attributes:" : "brunobb 07/24/2023 06:35",
		"attributesSize" : "brunobb 07/24/2023 06:35",
		"collectCategories" : "brunobb 07/24/2023 06:35",
		"convertedValuesDo:" : "brunobb 07/24/2023 06:35",
		"convertedValuesOnDate:do:" : "brunobb 07/24/2023 06:35",
		"convertedValuesOnYear:month:do:" : "brunobb 07/24/2023 06:35",
		"convertedValuesSelect:do:" : "brunobb 07/24/2023 06:35",
		"expensesCollectionWithCategoryAndAmountForYear:month:" : "brunobb 07/24/2023 08:04",
		"expensesValuesOnYear:month:do:" : "brunobb 07/24/2023 06:35",
		"includesAttributeNamed:" : "brunobb 07/24/2023 06:35",
		"moneyfyLinesAt:ifAbsent:" : "brunobb 07/24/2023 06:35",
		"moneyfyLinesSize" : "brunobb 07/24/2023 06:35",
		"originalString" : "brunobb 07/24/2023 06:35",
		"originalString:" : "brunobb 07/24/2023 06:35",
		"parse" : "brunobb 07/24/2023 06:35",
		"parseMonefyLine:" : "brunobb 07/24/2023 06:35",
		"parsedLineAt:do:" : "brunobb 07/24/2023 06:35",
		"setReadStream:" : "brunobb 07/24/2023 06:35",
		"setReadStream:root:" : "brunobb 07/24/2023 06:42",
		"systemRoot" : "brunobb 07/24/2023 06:42" } }
